{
	"info": {
		"_postman_id": "67c212c6-7419-4908-929d-9692378c7b0b",
		"name": "Udacity Regression Test Suit",
		"schema": "https://schema.getpostman.com/json/collection/v2.1.0/collection.json"
	},
 	"item": [
 		{
 			"name": "Create employee",
 			"event": [
 				{
 					"listen": "test",
 					"script": {
 						"exec": [
 							"pm.test(\"Successful response\", function () {",
 							"    pm.expect(pm.response.text()).to.include(\"id\");",
 							"});",
 							"",
 							"pm.test(\"Status code is 200\", function () {",
 							"    pm.response.to.have.status(200);",
 							"});"
 						],
 						"type": "text/javascript"
 					}
 				}
 			],
			"request": {
				"method": "POST",
				"header": [],
				"body": {
					"mode": "raw",
					"raw": "{\n    \"id\": \"{{id}}\",\n    \"idBook\": \"{{idBook}}\",\n    \"firstName\": \"{{FirstName}}\"\n    \"lastName\": \"{{LastName}}\"\n}",
					"options": {
						"raw": {
							"language": "json"
						}
					}
				},
				"url": {
					"raw": "https://dummy.restapiexample.com/api/v1/create",
					"protocol": "https",
					"host": [
					   "dummy",
					   "restapiexample",
					   "com"
					],
					"path": [
						"api",
						"v1",
						"create"
					]
				}
			},
			"response": []
		},
		{
			"name": "Get All employees",
			"event": [
				{
					"listen": "test",
					"script": {
						"exec": [
							"pm.test(\"Successful response\", function () {",
							"    pm.expect(pm.response.code).to.eq(200);",
							"});"
						],
						"type": "text/javascript"
					}
				}
			],
			"request": {
				"method": "GET",
				"header": [],
				"url": {
					"raw": "https://dummy.restapiexample.com/api/v1/employees",
					"protocol": "https",
					"host": [
					   "dummy",
					   "restapiexample",
					   "net"
					],
					"path": [
						"api",
						"v1",
						"employees"
					]
				}
			},
			"response": []
		},
		{
			"name": "Get employee",
			"event": [
				{
					"listen": "test",
					"script": {
						"exec": [
							"pm.test(\"Successful response\", function () {",
							"    pm.expect(pm.response.code).to.eq(200);",
							"});"
						],
						"type": "text/javascript"
					}
				}
			],
			"request": {
				"method": "GET",
				"header": [],
				"url": {
					"raw": "https://dummy.restapiexample.com/api/v1/employee/1",
					"protocol": "https",
					"host": [
						"dummy",
						"restapiexample",
						"com"
					 ],
					 "path": [
						 "api",
						 "v1",
						 "employee",
						 "1"
					 ]
				},
				"description": "Get a single employee data"
			},
			"response": []
		},
		{
			"name": "Update employee",
			"event": [
				{
					"listen": "test",
					"script": {
						"exec": [
							"pm.test(\"Successful response\", function () {",
							"    pm.expect(pm.response.code).to.eq(200);",
							"});"
						],
						"type": "text/javascript"
					}
				}
			],
			"request": {
				"method": "POST",
				"header": [],
				"body": {
					"mode": "raw",
					"raw": "{\n    \"id\": \"{{new_id}}\",\n}",   
					"options": {
						"raw": {
							"language": "json"
						}
					}
				},
				"url": {
					"raw": "https://dummy.restapiexample.com/api/v1/update/21/",
					"protocol": "https",
					"host": [
						"dummy",
						"restapiexample",
						"com"
					 ],
					 "path": [
						 "api",
						 "v1",
						 "update",
						 "21"
					 ]
				},
				"description": "Update an employee record"
			},
			"response": []
		},
		{
			"name": "Delete employee",
			"event": [
				{
					"listen": "test",
					"script": {
						"exec": [
							"pm.test(\"Successful response\", function () {",
							"    pm.expect(pm.response.code).to.eq(200);",
							"});"
						],
						"type": "text/javascript"
					}
				}
			],
			"request": {
				"method": "DELETE",
				"header": [],
				"url": {
					"raw": "https://dummy.restapiexample.com/api/v1/delete/2/",
					"protocol": "https",
					"host": [
						"restapiexample",
						"restapiexample",
						"net"
					 ],
					 "path": [
						 "api",
						 "v1",
						 "employee",
						 "2"
					 ]
				},
				"description": "Delete an employee record"
			},
			"response": []
		}
	],
	"event": [
		{
			"listen": "prerequest",
			"script": {
				"type": "text/javascript",
				"exec": [
					""
				]
			}
		},
		{
			"listen": "test",
			"script": {
				"type": "text/javascript",
				"exec": [
					""
				]
			}
		}
	]
}